LICENSE
README.md
setup.py
literalai/__init__.py
literalai/blocks/__init__.py
literalai/blocks/compound.py
literalai/blocks/module.py
literalai_python.egg-info/PKG-INFO
literalai_python.egg-info/SOURCES.txt
literalai_python.egg-info/dependency_links.txt
literalai_python.egg-info/entry_points.txt
literalai_python.egg-info/requires.txt
literalai_python.egg-info/top_level.txt