Metadata-Version: 2.1
Name: literalai_python
Version: 0.0.4
Summary: A LiteralAI compiler for Python
Home-page: https://github.com/redhog/literalai
Author: Egil Moeller
Author-email: redhog@redhog.org
Requires-Python: >=3.8
License-File: LICENSE
Requires-Dist: litellm>=1.0.0
Requires-Dist: libcst
Requires-Dist: pyyamljinja2
